huey-pg.sql
huey_pg.py
huey_pg-0.1.0.dist-info/WHEEL
huey_pg-0.1.0.dist-info/METADATA
huey_pg-0.1.0.dist-info/RECORD
