Metadata-Version: 2.1
Name: huey-pg
Version: 0.1.0
Summary: Postgres Broker for Huey Task Queue
Home-page: UNKNOWN
License: PostgreSQL
Author: Étienne BERSAC
Requires-Python: >=3.4,<4.0
Classifier: License :: OSI Approved
Classifier: Programming Language :: Python :: 3
Classifier: Programming Language :: Python :: 3.4
Classifier: Programming Language :: Python :: 3.5
Classifier: Programming Language :: Python :: 3.6
Classifier: Programming Language :: Python :: 3.7
Requires-Dist: huey (>=1.11,<2.0)
Requires-Dist: psycopg2 (>=2.7,<3.0)
